acd_sdk/__init__.py
acd_sdk/common.py
acd_sdk/version.py
acd_sdk/annotator_for_clinical_data/__init__.py
acd_sdk/annotator_for_clinical_data/annotator_for_clinical_data_v1.py
acd_sdk/annotator_for_clinical_data/tests/__init__.py
acd_sdk/annotator_for_clinical_data/tests/common/__init__.py
acd_sdk/annotator_for_clinical_data/tests/common/test_annotation.py
acd_sdk/annotator_for_clinical_data/tests/common/test_annotator_output.py
acd_sdk/annotator_for_clinical_data/tests/common/test_assistance_annotation.py
acd_sdk/annotator_for_clinical_data/tests/common/test_attribute_values.py
acd_sdk/annotator_for_clinical_data/tests/common/test_cancer_diagnosis.py
acd_sdk/annotator_for_clinical_data/tests/common/test_concept_annotation.py
acd_sdk/annotator_for_clinical_data/tests/common/test_concept_value_annotation.py
acd_sdk/annotator_for_clinical_data/tests/common/test_disambiguation.py
acd_sdk/annotator_for_clinical_data/tests/common/test_ejection_fraction.py
acd_sdk/annotator_for_clinical_data/tests/common/test_insight_model.py
acd_sdk/annotator_for_clinical_data/tests/common/test_lab_value.py
acd_sdk/annotator_for_clinical_data/tests/common/test_medication.py
acd_sdk/annotator_for_clinical_data/tests/common/test_negated_span.py
acd_sdk/annotator_for_clinical_data/tests/common/test_nlu_entities.py
acd_sdk/annotator_for_clinical_data/tests/common/test_procedure.py
acd_sdk/annotator_for_clinical_data/tests/common/test_relation.py
acd_sdk/annotator_for_clinical_data/tests/common/test_section.py
acd_sdk/annotator_for_clinical_data/tests/common/test_smoking.py
acd_sdk/annotator_for_clinical_data/tests/common/test_spell_corrected_text.py
acd_sdk/annotator_for_clinical_data/tests/common/test_spelling_correction.py
acd_sdk/annotator_for_clinical_data/tests/common/test_suggestion.py
acd_sdk/annotator_for_clinical_data/tests/common/test_symptom_disease.py
acd_sdk/annotator_for_clinical_data/tests/common/test_temporal_span.py
acd_sdk-2.0.2.dist-info/LICENSE.md
acd_sdk-2.0.2.dist-info/METADATA
acd_sdk-2.0.2.dist-info/WHEEL
acd_sdk-2.0.2.dist-info/top_level.txt
acd_sdk-2.0.2.dist-info/zip-safe
acd_sdk-2.0.2.dist-info/RECORD
