Metadata-Version: 2.1
Name: acd-sdk
Version: 2.0.2
Summary: ('This is the Annotator for Clinical Data Python SDK',)
Home-page: https://github.com/Merative/acd-python-sdk
Author: Merative
Author-email: acddev@merative.com
License: Apache 2.0
Keywords: PACKAGE_NAME
Classifier: Programming Language :: Python
Classifier: Programming Language :: Python :: 3
Classifier: Programming Language :: Python :: 3.7
Classifier: Programming Language :: Python :: 3.8
Classifier: Programming Language :: Python :: 3.9
Classifier: Programming Language :: Python :: 3.10
Classifier: Development Status :: 4 - Beta
Classifier: Intended Audience :: Developers
Classifier: License :: OSI Approved :: Apache Software License
Classifier: Operating System :: OS Independent
Classifier: Topic :: Software Development :: Libraries :: Python Modules
Classifier: Topic :: Software Development :: Libraries :: Application Frameworks
License-File: LICENSE.md
Requires-Dist: requests (<3.0,>=2.24.0)
Requires-Dist: python-dateutil (<3.0.0,>=2.5.3)
Requires-Dist: ibm-cloud-sdk-core (<4.0.0,==3.16.0)
